<PAMDataset>
  <PAMRasterBand band="1">
    <Histograms>
      <HistItem>
        <HistMin>264.0862426757812</HistMin>
        <HistMax>292.0032043457031</HistMax>
        <BucketCount>256</BucketCount>
        <IncludeOutOfRange>1</IncludeOutOfRange>
        <Approximate>0</Approximate>
        <HistCounts>1|3|1|1|1|1|2|0|0|1|4|1|2|1|3|2|3|4|16|21|200|284|170|142|88|96|114|99|118|136|122|106|87|100|94|101|96|117|139|183|189|149|160|183|384|1042|800|413|245|401|1374|1792|2728|2104|1871|2643|3397|5159|3685|3105|2769|3602|3126|5576|4016|3257|4270|3602|3229|3486|3505|2386|1921|2053|2376|3295|2948|2386|2065|1925|2273|2405|2565|2526|2604|2843|3007|3080|3189|3573|3498|3210|3477|3590|4142|4205|4601|4625|4534|4498|4160|3786|3516|3303|3181|3039|2805|2647|2787|2737|2772|2771|2702|2698|2513|2706|2643|2573|2439|2010|1646|1535|1438|1266|1259|1151|1189|1164|1110|1050|981|963|892|791|795|814|818|835|753|665|640|618|605|528|570|576|524|456|409|365|353|393|367|368|353|313|340|305|287|288|291|279|279|279|325|296|260|245|277|271|292|270|258|283|260|247|212|199|212|203|219|234|225|225|185|173|150|147|139|163|139|159|176|154|124|110|105|120|109|102|83|73|82|72|64|68|61|56|49|56|45|42|34|36|29|34|38|33|22|23|20|21|15|18|12|21|24|26|37|42|37|39|34|20|29|9|10|5|10|8|3|5|5|2|0|0|3|1|0|0|2|0|3|2|1|1</HistCounts>
      </HistItem>
    </Histograms>
  </PAMRasterBand>
</PAMDataset>
